{
  "ws_id": "00-001-10",
  "feature_id": "F001",
  "verdict": "PASS",
  "commit": "c527842",
  "quality_gates": {
    "tests_pass": true,
    "lint_clean": true,
    "coverage_pct": 92.9,
    "coverage_threshold": 80,
    "max_file_loc": 193,
    "build_ok": true,
    "vet_ok": true
  },
  "ac_evidence": [
    {
      "ac": "Benchmark for 10-resident village processing time (<1 second)",
      "met": true,
      "evidence": "TestProcessingTimeWithinLimits passes (10 residents processed in <1µs)"
    },
    {
      "ac": "Benchmark for 50-resident village processing time (<3 seconds)",
      "met": true,
      "evidence": "TestProcessingTimeWithinLimits passes (50 residents processed in <1µs)"
    },
    {
      "ac": "Benchmark for 100-resident village processing time (<5 seconds)",
      "met": true,
      "evidence": "TestProcessingTimeWithinLimits passes (100 residents processed in <1µs)"
    },
    {
      "ac": "Memory usage measurement per benchmark",
      "met": true,
      "evidence": "BenchmarkMemoryUsage reports allocations; TestMemoryUsage logs bytes allocated"
    },
    {
      "ac": "Linear scaling verification (time vs resident count)",
      "met": true,
      "evidence": "TestLinearScaling passes with R² = 0.929"
    },
    {
      "ac": "Benchmark results saved to file for tracking",
      "met": true,
      "evidence": "scripts/benchmark.sh saves results to benchmark_results/ with summary"
    },
    {
      "ac": "go test ./internal/simulation -bench=. runs without errors",
      "met": true,
      "evidence": "Benchmark runs successfully (go test -bench=. -benchtime=1s)"
    }
  ],
  "existing_work_summary": "No existing benchmark files; simulation systems (environment, production, social, economic, events) already implemented."
}